{
  "atomIcon.png": {
    "text": [
      "Copyright 2002-2015 University of Colorado Boulder"
    ],
    "projectURL": "https://phet.colorado.edu",
    "license": "contact phethelp@colorado.edu",
    "notes": "created by Sharon Siman-Tov"
  },
  "atomIconSmall.png": {
    "text": [
      "Copyright 2002-2015 University of Colorado Boulder"
    ],
    "projectURL": "https://phet.colorado.edu",
    "license": "contact phethelp@colorado.edu",
    "notes": "created by John Blanco"
  },
  "elementIcon.png": {
    "text": [
      "Copyright 2002-2015 University of Colorado Boulder"
    ],
    "projectURL": "https://phet.colorado.edu",
    "license": "contact phethelp@colorado.edu",
    "notes": "created by Sharon Siman-Tov"
  },
  "elementIconSmall.png": {
    "text": [
      "Copyright 2002-2015 University of Colorado Boulder"
    ],
    "projectURL": "https://phet.colorado.edu",
    "license": "contact phethelp@colorado.edu",
    "notes": "created by John Blanco and Sharon Siman-Tov"
  },
  "gameIcon.png": {
    "text": [
      "Copyright 2002-2015 University of Colorado Boulder"
    ],
    "projectURL": "https://phet.colorado.edu",
    "license": "contact phethelp@colorado.edu",
    "notes": "created by Sharon Siman-Tov"
  },
  "gameIconSmall.png": {
    "text": [
      "Copyright 2002-2015 University of Colorado Boulder"
    ],
    "projectURL": "https://phet.colorado.edu",
    "license": "contact phethelp@colorado.edu",
    "notes": "created by John Blanco and Sharon Siman-Tov"
  },
  "massChargeIcon.png": {
    "text": [
      "Copyright 2002-2015 University of Colorado Boulder"
    ],
    "projectURL": "https://phet.colorado.edu",
    "license": "contact phethelp@colorado.edu",
    "notes": "created by John Blanco"
  },
  "periodicTableIcon.png": {
    "text": [
      "Copyright 2002-2015 University of Colorado Boulder"
    ],
    "projectURL": "https://phet.colorado.edu",
    "license": "contact phethelp@colorado.edu",
    "notes": "created by John Blanco"
  },
  "questionMarkIcon.png": {
    "text": [
      "Copyright 2002-2015 University of Colorado Boulder"
    ],
    "projectURL": "https://phet.colorado.edu",
    "license": "contact phethelp@colorado.edu",
    "notes": "created by John Blanco"
  },
  "scale.png": {
    "text": [
      "Copyright 2002-2015 University of Colorado Boulder"
    ],
    "projectURL": "https://phet.colorado.edu",
    "license": "contact phethelp@colorado.edu",
    "notes": "created by Sharon Siman-Tov"
  },
  "symbolQuestionIcon.png": {
    "text": [
      "Copyright 2002-2015 University of Colorado Boulder"
    ],
    "projectURL": "https://phet.colorado.edu",
    "license": "contact phethelp@colorado.edu",
    "notes": "created by John Blanco"
  }
}